{
	"info": {
		"_postman_id": "50457373-5341-476e-8bbb-d7033366f112",
		"name": "Project 2 Campaign Controller",
		"schema": "https://schema.getpostman.com/json/collection/v2.1.0/collection.json"
	},
	"item": [
		{
			"name": "Create Campaign",
			"request": {
				"method": "POST",
				"header": [],
				"body": {
					"mode": "raw",
					"raw": "{\r\n    \"name\":\"New York 5\",\r\n    \"playerCount\": 0\r\n}",
					"options": {
						"raw": {
							"language": "json"
						}
					}
				},
				"url": {
					"raw": "http://localhost:8000/campaign/createCampaign",
					"protocol": "http",
					"host": [
						"localhost"
					],
					"port": "8000",
					"path": [
						"campaign",
						"createCampaign"
					],
					"query": [
						{
							"key": "",
							"value": "",
							"disabled": true
						}
					]
				}
			},
			"response": []
		},
		{
			"name": "Get Campaign by Name",
			"protocolProfileBehavior": {
				"disableBodyPruning": true
			},
			"request": {
				"method": "GET",
				"header": [],
				"body": {
					"mode": "raw",
					"raw": "",
					"options": {
						"raw": {
							"language": "json"
						}
					}
				},
				"url": {
					"raw": "http://localhost:8000/campaign/getCampaign?name=Dwindurin",
					"protocol": "http",
					"host": [
						"localhost"
					],
					"port": "8000",
					"path": [
						"campaign",
						"getCampaign"
					],
					"query": [
						{
							"key": "name",
							"value": "Dwindurin"
						}
					]
				}
			},
			"response": []
		},
		{
			"name": "Get All Campaigns",
			"protocolProfileBehavior": {
				"disableBodyPruning": true
			},
			"request": {
				"method": "GET",
				"header": [],
				"body": {
					"mode": "raw",
					"raw": "",
					"options": {
						"raw": {
							"language": "json"
						}
					}
				},
				"url": {
					"raw": "http://localhost:8000/campaign/getAll",
					"protocol": "http",
					"host": [
						"localhost"
					],
					"port": "8000",
					"path": [
						"campaign",
						"getAll"
					]
				}
			},
			"response": []
		},
		{
			"name": "Select Campaign for User",
			"request": {
				"method": "POST",
				"header": [],
				"url": {
					"raw": "http://localhost:8000/campaign/selectCampaign?name=Atlantis",
					"protocol": "http",
					"host": [
						"localhost"
					],
					"port": "8000",
					"path": [
						"campaign",
						"selectCampaign"
					],
					"query": [
						{
							"key": "name",
							"value": "Atlantis"
						}
					]
				}
			},
			"response": []
		}
	]
}